snbpy/__init__.py
snbpy/snb_api_client.py
snbpy/common/__init__.py
snbpy/common/component/__init__.py
snbpy/common/component/local_cache.py
snbpy/common/constant/__init__.py
snbpy/common/constant/exceptions.py
snbpy/common/constant/snb_constant.py
snbpy/common/domain/__init__.py
snbpy/common/domain/request.py
snbpy/common/domain/response.py
snbpy/common/domain/snb_config.py
snbpy/common/util/__init__.py
snbpy/common/util/array_utils.py
snbpy/common/util/config_reader.py
snbpy/common/util/string_utils.py
snbpy-1.0.7.dist-info/LICENSE
snbpy-1.0.7.dist-info/LICENSES
snbpy-1.0.7.dist-info/METADATA
snbpy-1.0.7.dist-info/WHEEL
snbpy-1.0.7.dist-info/top_level.txt
snbpy-1.0.7.dist-info/RECORD
