Metadata-Version: 2.1
Name: snbpy
Version: 1.0.7
Summary: snbpy
Home-page: https://www.snowballsecurities.com
Author: SNB
Author-email: service@xueqiu.com
Project-URL: Bug Reports, https://github.com/snowballsecurities/snbpy/issues
Project-URL: Funding, https://www.snowballsecurities.com
Project-URL: Say Thanks!, https://www.snowballsecurities.com
Project-URL: Source, https://github.com/snowballsecurities/snbpy
Keywords: snbpy
Classifier: Development Status :: 3 - Alpha
Classifier: Intended Audience :: Developers
Classifier: Topic :: Software Development :: Build Tools
Classifier: License :: OSI Approved :: MIT License
Classifier: Programming Language :: Python :: 3
Classifier: Programming Language :: Python :: 3.5
Classifier: Programming Language :: Python :: 3.6
Classifier: Programming Language :: Python :: 3.7
Classifier: Programming Language :: Python :: 3.8
Classifier: Programming Language :: Python :: 3 :: Only
Requires-Python: >=3.6, <4
License-File: LICENSE
License-File: LICENSES
Requires-Dist: requests
